stemfard/__init__.py
stemfard/core.py
stemfard-0.0.2.dist-info/licenses/LICENSE.txt
stemfard-0.0.2.dist-info/METADATA
stemfard-0.0.2.dist-info/WHEEL
stemfard-0.0.2.dist-info/top_level.txt
stemfard-0.0.2.dist-info/RECORD
