Metadata-Version: 2.4
Name: stemfard
Version: 0.0.2
Summary: A Python library for mathematical and Statistical Computing in Science, Technology, Engineering and Mathematics (STEM).
Author-email: STEM Research <stemfard@stemfard.org>
License: MIT
Project-URL: Homepage, https://github.com/stemfard/stemfard
Project-URL: Documentation, https://github.com/stemfard/stemfard#readme
Project-URL: Source, https://github.com/stemfard/stemfard
Keywords: linear algebra
Classifier: Development Status :: 3 - Alpha
Classifier: Intended Audience :: Education
Classifier: Intended Audience :: Science/Research
Classifier: License :: OSI Approved :: MIT License
Classifier: Programming Language :: Python :: 3
Classifier: Programming Language :: Python :: 3.9
Classifier: Programming Language :: Python :: 3.10
Classifier: Programming Language :: Python :: 3.11
Classifier: Programming Language :: Python :: 3.12
Classifier: Topic :: Scientific/Engineering :: Mathematics
Requires-Python: >=3.9
License-File: LICENSE.txt
Requires-Dist: sympy>=1.12
Dynamic: license-file
